numcat/__init__.py
numcat/functions.py
numcat-0.0.1.dist-info/LICENSE
numcat-0.0.1.dist-info/METADATA
numcat-0.0.1.dist-info/WHEEL
numcat-0.0.1.dist-info/top_level.txt
numcat-0.0.1.dist-info/RECORD
