Metadata-Version: 2.1
Name: numcat
Version: 0.0.1
Summary: A Package that allows concatenation of numbers.
Home-page: https://github.com/archiejesty/numcat
Author: Archie Jesty
License: UNKNOWN
Project-URL: Bug Tracker, https://github.com/archiejesty/numcat/issues
Platform: UNKNOWN
Classifier: Programming Language :: Python :: 3
Classifier: License :: OSI Approved :: MIT License
Classifier: Operating System :: OS Independent
Requires-Python: >=3.6
License-File: LICENSE
